sematic/__init__.py
sematic/abstract_calculator.py
sematic/abstract_future.py
sematic/abstract_plugin.py
sematic/api/app.py
sematic/api/endpoints/artifacts.py
sematic/api/endpoints/auth.py
sematic/api/endpoints/edges.py
sematic/api/endpoints/events.py
sematic/api/endpoints/external_resources.py
sematic/api/endpoints/meta.py
sematic/api/endpoints/notes.py
sematic/api/endpoints/request_parameters.py
sematic/api/endpoints/resolutions.py
sematic/api/endpoints/runs.py
sematic/api/server.py
sematic/api/wsgi.py
sematic/api_client.py
sematic/caching/__init__.py
sematic/caching/caching.py
sematic/calculator.py
sematic/cli/cancel.py
sematic/cli/cli.py
sematic/cli/examples_utils.py
sematic/cli/logs.py
sematic/cli/main.py
sematic/cli/migrate.py
sematic/cli/new.py
sematic/cli/process_utils.py
sematic/cli/run.py
sematic/cli/settings.py
sematic/cli/start.py
sematic/cli/stop.py
sematic/cli/version.py
sematic/client.py
sematic/config/config.py
sematic/config/config_dir.py
sematic/config/server_settings.py
sematic/config/settings.py
sematic/config/user_settings.py
sematic/container_images.py
sematic/db/db.py
sematic/db/migrate.py
sematic/db/migrations/20220424062956_create_runs_table.sql
sematic/db/migrations/20220514015440_create_artifacts_table.sql
sematic/db/migrations/20220519154144_add_description_tags_to_runs.sql
sematic/db/migrations/20220521155045_add_source_code_to_runs.sql
sematic/db/migrations/20220521155336_add_root_id_to_runs.sql
sematic/db/migrations/20220522082435_add_type_serialization_to_artifacts.sql
sematic/db/migrations/20220527000512_add_edges_table.sql
sematic/db/migrations/20220610234559_create_notes_table.sql
sematic/db/migrations/20220714175433_add_nested_future_id_to_runs.sql
sematic/db/migrations/20220723010628_create_users_table.sql
sematic/db/migrations/20220726001230_add_exception_to_runs_table.sql
sematic/db/migrations/20220816235619_resolutions.sql
sematic/db/migrations/20220819172555_external_jobs.sql
sematic_ee-0.0.1.dist-info/METADATA
sematic_ee-0.0.1.dist-info/RECORD
sematic_ee-0.0.1.dist-info/WHEEL
sematic_ee-0.0.1.dist-info/entry_points.txt
