Metadata-Version: 2.1
Name: sematic-ee
Version: 0.0.1
Author: Sematic AI, Inc.
Author-email: emmanuel@sematic.ai
Home-page: https://sematic.dev
License: Proprietary
Classifier: License :: OSI Approved :: MIT License
Classifier: Intended Audience :: Developers
Classifier: Intended Audience :: Science/Research
Classifier: Programming Language :: Python :: 3 :: Only
Classifier: Topic :: Scientific/Engineering :: Artificial Intelligence
Classifier: Topic :: Scientific/Engineering :: Visualization
Classifier: Typing :: Typed
Requires-Python: >=3.8,<3.10
Requires-Dist: eventlet==0.30.2
Requires-Dist: SQLAlchemy<2.0.0
Requires-Dist: ray>=2.1.0
Requires-Dist: setuptools
Requires-Dist: PyYAML
Requires-Dist: python-dateutil
Requires-Dist: six
Requires-Dist: cloudpickle
Requires-Dist: requests
Requires-Dist: certifi
Requires-Dist: charset-normalizer
Requires-Dist: idna
Requires-Dist: urllib3
Requires-Dist: git-python
Requires-Dist: GitPython
Requires-Dist: gitdb
Requires-Dist: smmap
Requires-Dist: python-socketio
Requires-Dist: bidict
Requires-Dist: python-engineio
Requires-Dist: websocket-client
Requires-Dist: mpld3
Requires-Dist: Jinja2
Requires-Dist: MarkupSafe
Requires-Dist: matplotlib
Requires-Dist: contourpy
Requires-Dist: numpy
Requires-Dist: cycler
Requires-Dist: fonttools
Requires-Dist: kiwisolver
Requires-Dist: packaging
Requires-Dist: pyparsing
Requires-Dist: Pillow
Requires-Dist: boto3
Requires-Dist: botocore
Requires-Dist: jmespath
Requires-Dist: s3transfer
Requires-Dist: psycopg2-binary
Requires-Dist: click
Requires-Dist: Flask
Requires-Dist: importlib-metadata
Requires-Dist: zipp
Requires-Dist: itsdangerous
Requires-Dist: Werkzeug
Requires-Dist: gunicorn
Requires-Dist: Flask-Cors
Requires-Dist: google-auth
Requires-Dist: cachetools
Requires-Dist: pyasn1-modules
Requires-Dist: rsa
Requires-Dist: Flask-SocketIO
Requires-Dist: kubernetes
Requires-Dist: requests-oauthlib
Requires-Dist: oauthlib
Requires-Dist: dnspython
Requires-Dist: greenlet
Requires-Dist: colorama
Requires-Dist: psutil
Requires-Dist: setproctitle
Requires-Dist: aiosignal
Requires-Dist: frozenlist
Requires-Dist: attrs
Requires-Dist: filelock
Requires-Dist: grpcio
Requires-Dist: jsonschema
Requires-Dist: importlib-resources
Requires-Dist: pkgutil-resolve-name
Requires-Dist: pyrsistent
Requires-Dist: msgpack
Requires-Dist: protobuf
Requires-Dist: virtualenv
Requires-Dist: distlib
Requires-Dist: platformdirs
